graphbench/__init__.py
graphbench/datasets.csv
graphbench/evaluator.py
graphbench/loader.py
graphbench/master.csv
graphbench/optimize.py
graphbench/algoreas_helpers/__init__.py
graphbench/algoreas_helpers/algoreas_utils.py
graphbench/co_helpers/__init__.py
graphbench/co_helpers/parallelize_with_progress_bar.py
graphbench/co_helpers/split_dataset.py
graphbench/co_helpers/datasets/__init__.py
graphbench/co_helpers/datasets/ba_dataset.py
graphbench/co_helpers/datasets/er_dataset.py
graphbench/co_helpers/datasets/rb_dataset.py
graphbench/co_helpers/datasets/synthetic_dataset.py
graphbench/datasets/__init__.py
graphbench/datasets/algoreas.py
graphbench/datasets/bluesky.py
graphbench/datasets/chipdesign.py
graphbench/datasets/combinatorial_optimization.py
graphbench/datasets/electroniccircuits.py
graphbench/datasets/sat.py
graphbench/datasets/weatherforecasting.py
graphbench/helpers/__init__.py
graphbench/helpers/download.py
graphbench/helpers/utils.py
graphbench/tests/test_graphbench.py
graphbench/weatherforecasting_helpers/losses.py
graphbench_lib-0.1.2.4.dist-info/licenses/LICENSE
graphbench_lib-0.1.2.4.dist-info/METADATA
graphbench_lib-0.1.2.4.dist-info/WHEEL
graphbench_lib-0.1.2.4.dist-info/top_level.txt
graphbench_lib-0.1.2.4.dist-info/RECORD
